setup.py
Tic_Toc_Toe_Elham/__init__.py
Tic_Toc_Toe_Elham/python_code.py
Tic_Toc_Toe_Elham.egg-info/PKG-INFO
Tic_Toc_Toe_Elham.egg-info/SOURCES.txt
Tic_Toc_Toe_Elham.egg-info/dependency_links.txt
Tic_Toc_Toe_Elham.egg-info/not-zip-safe
Tic_Toc_Toe_Elham.egg-info/top_level.txt