Metadata-Version: 1.0
Name: Tic-Toc-Toe-Elham
Version: 0.1
Summary: Tic_Toc_Toe_game
Home-page: UNKNOWN
Author: UNKNOWN
Author-email: UNKNOWN
License: UNKNOWN
Platform: UNKNOWN
